arvos/__init__.py
arvos/client.py
arvos/data_types.py
arvos/server.py
arvos_sdk-1.0.0.dist-info/licenses/LICENSE
arvos_sdk-1.0.0.dist-info/METADATA
arvos_sdk-1.0.0.dist-info/WHEEL
arvos_sdk-1.0.0.dist-info/top_level.txt
arvos_sdk-1.0.0.dist-info/RECORD
