Metadata-Version: 2.4
Name: arvos-sdk
Version: 1.0.0
Summary: Python SDK for receiving sensor data from Arvos iPhone app
Home-page: https://github.com/jaskirat1616/arvos-sdk
Author: Jaskirat Singh
Author-email: jaskirat1616@gmail.com
Classifier: Development Status :: 4 - Beta
Classifier: Intended Audience :: Developers
Classifier: Intended Audience :: Science/Research
Classifier: Topic :: Scientific/Engineering
Classifier: Topic :: Software Development :: Libraries :: Python Modules
Classifier: License :: OSI Approved :: MIT License
Classifier: Programming Language :: Python :: 3
Classifier: Programming Language :: Python :: 3.8
Classifier: Programming Language :: Python :: 3.9
Classifier: Programming Language :: Python :: 3.10
Classifier: Programming Language :: Python :: 3.11
Requires-Python: >=3.8
License-File: LICENSE
Requires-Dist: websockets>=11.0
Requires-Dist: qrcode[pil]>=7.4
Requires-Dist: numpy>=1.20.0
Provides-Extra: visualization
Requires-Dist: matplotlib>=3.5.0; extra == "visualization"
Provides-Extra: image
Requires-Dist: Pillow>=9.0.0; extra == "image"
Requires-Dist: opencv-python>=4.5.0; extra == "image"
Provides-Extra: ros2
Requires-Dist: rclpy; extra == "ros2"
Requires-Dist: cv_bridge; extra == "ros2"
Provides-Extra: dev
Requires-Dist: pytest>=7.0.0; extra == "dev"
Requires-Dist: black>=22.0.0; extra == "dev"
Requires-Dist: flake8>=4.0.0; extra == "dev"
Dynamic: author
Dynamic: author-email
Dynamic: classifier
Dynamic: description
Dynamic: description-content-type
Dynamic: home-page
Dynamic: license-file
Dynamic: provides-extra
Dynamic: requires-dist
Dynamic: requires-python
Dynamic: summary
